notion_exporter/__init__.py
notion_exporter/block_converter.py
notion_exporter/exporter.py
notion_exporter/property_converter.py
notion_exporter/retry_utils.py
notion_exporter-0.1.0.dist-info/METADATA
notion_exporter-0.1.0.dist-info/WHEEL
notion_exporter-0.1.0.dist-info/licenses/LICENSE
notion_exporter-0.1.0.dist-info/RECORD
