Metadata-Version: 2.1
Name: notion-exporter
Version: 0.1.0
Summary: Tool that allows you to export your Notion pages to markdown files.
Project-URL: GitHub: repo, https://github.com/deepset-ai/haystack
Author-email: Bogdan Kostić <bogdankostic@web.de>
License-Expression: Apache-2.0
License-File: LICENSE
Keywords: Notion,Notion-API,Notion-Export,Notion-Extraction
Requires-Python: >=3.8
Requires-Dist: notion-client
Requires-Dist: notion2md
Requires-Dist: tenacity
